copi/__init__.py
copi/books/__init__.py
copi/lets/__init__.py
copi/lib/__init__.py
copi/py.typed
copi/tests/__init__.py
copi/tests/test_mod.py
copi/types/__init__.py
copi-0.1.1.dist-info/LICENSE
copi-0.1.1.dist-info/METADATA
copi-0.1.1.dist-info/WHEEL
copi-0.1.1.dist-info/RECORD
