Metadata-Version: 2.1
Name: copi
Version: 0.1.1
Summary: Build smart applications powered by Conversational Copilots.
License: Creative Commons Attribution-NonCommercial-ShareAlike 4.0 International Public License
Author: Al Wonder
Author-email: al@yiwonder.com
Requires-Python: >=3.10,<4.0
Classifier: License :: Other/Proprietary License
Classifier: Programming Language :: Python :: 3
Classifier: Programming Language :: Python :: 3.10
Classifier: Programming Language :: Python :: 3.11
Classifier: Programming Language :: Python :: 3.12
Provides-Extra: all
Provides-Extra: cli
Provides-Extra: llm
Requires-Dist: openai (>=1.12.0,<2.0.0) ; extra == "all" or extra == "llm"
Requires-Dist: openapi (>=1.1.0,<2.0.0)
Requires-Dist: typer[all] (>=0.9.0,<0.10.0) ; extra == "all" or extra == "cli"
